laundromat/__init__.py
laundromat/regex_engine/__init__.py
laundromat/regex_engine/alder.py
laundromat/regex_engine/amount.py
laundromat/regex_engine/credit_card.py
laundromat/regex_engine/date_time.py
laundromat/regex_engine/fnr.py
laundromat/regex_engine/generic.py
laundromat/regex_engine/kontonummer.py
laundromat/regex_engine/regex_base.py
laundromat/regex_engine/tlfnr.py
laundromat/spacy/__init__.py
laundromat/spacy/list_merger.py
laundromat/spacy/matcher_list.py
laundromat/spacy/matcher_regex.py
laundromat/spacy/regex_formatter.py
laundromat/spacy/spacy_model.py
laundromat/spacy/data/etternavn_ssb.csv
laundromat/spacy/data/guttefornavn_ssb.csv
laundromat/spacy/data/jentefornavn_ssb.csv
laundromat/spacy/data/land.csv
laundromat-1.1.5.dist-info/METADATA
laundromat-1.1.5.dist-info/WHEEL
laundromat-1.1.5.dist-info/top_level.txt
laundromat-1.1.5.dist-info/RECORD
