Metadata-Version: 2.1
Name: laundromat
Version: 1.1.5
Summary: Scrub personal information from text with Laundromat.
Home-page: UNKNOWN
Author: Marius Dioli @ NAV IKT and Petter Sunde Nymark @ NAV IKT
License: MIT
Platform: UNKNOWN
Classifier: Development Status :: 5 - Production/Stable
Classifier: License :: OSI Approved :: MIT License
Classifier: Programming Language :: Python :: 3.6
Classifier: Programming Language :: Python :: 3.7
Requires-Python: >=3.6
Requires-Dist: spacy (>=2.3.0)
Requires-Dist: plac (>=1.1.3)
Requires-Dist: setuptools (>=40.8.0)
Requires-Dist: networkx (>=2.3)
Requires-Dist: pandas (>=1.0.0)
